README.rst
setup.py
cosmid/__init__.py
cosmid/core.py
cosmid/distribute_setup.py
cosmid/magicmethods.py
cosmid/messenger.py
cosmid/resource.py
cosmid/yml.py
cosmid.egg-info/PKG-INFO
cosmid.egg-info/SOURCES.txt
cosmid.egg-info/dependency_links.txt
cosmid.egg-info/requires.txt
cosmid.egg-info/top_level.txt
cosmid/resources/1000g_omni.py
cosmid/resources/1000g_snps.py
cosmid/resources/__init__.py
cosmid/resources/ccds.py
cosmid/resources/dbsnp.py
cosmid/resources/dbsnpex.py
cosmid/resources/decoy.py
cosmid/resources/ensembl_assembly.py
cosmid/resources/example.py
cosmid/resources/genbank.py
cosmid/resources/gtf.py
cosmid/resources/hapmap.py
cosmid/resources/indels.py
cosmid/resources/mills.py
cosmid/resources/ncbi_assembly.py
cosmid/resources/ucsc_assembly.py
cosmid/servers/__init__.py
cosmid/servers/ensembl.py
cosmid/servers/gatk.py
cosmid/servers/ncbi.py
cosmid/servers/thousandg.py
cosmid/servers/ucsc.py
scripts/cosmid