Metadata-Version: 1.1
Name: cosmid
Version: 0.4.9
Summary: A genomics resource manager
Home-page: https://github.com/robinandeer/cosmid
Author: Robin Andeer
Author-email: robin.andeer@scilifelab.se
License: MIT
Download-URL: https://github.com/robinandeer/cosmid/releases
Keywords: bioinformatics resource manager database genomics
Platform: UNKNOWN
Classifier: Development Status :: 3 - Alpha
Classifier: Natural Language :: English
Classifier: License :: OSI Approved :: MIT License
Classifier: Programming Language :: Python
